permission_manager_drf/__init__.py
permission_manager_drf/fields.py
permission_manager_drf/managers.py
permission_manager_drf/pagination.py
permission_manager_drf/permissions.py
permission_manager_drf/settings.py
permission_manager_drf/utils.py
permission_manager_drf-1.0.1.dist-info/METADATA
permission_manager_drf-1.0.1.dist-info/WHEEL
permission_manager_drf-1.0.1.dist-info/licenses/LICENSE
permission_manager_drf-1.0.1.dist-info/RECORD
