Metadata-Version: 2.4
Name: permission-manager-drf
Version: 1.0.1
Summary: A simple way to manage object permissions in drf.
Project-URL: Homepage, https://github.com/kindlycat/permission-manager-drf
Project-URL: Documentation, https://permission-manager-drf.readthedocs.io
Project-URL: Repository, https://github.com/kindlycat/permission-manager-drf.git
Project-URL: Issues, https://github.com/kindlycat/permission-manager-drf/issues
Author-email: Grigory Mishchenko <grishkokot@gmail.com>
License-Expression: MIT
License-File: LICENSE
Keywords: drf,permissions,rest framework
Classifier: Development Status :: 5 - Production/Stable
Classifier: Framework :: Django
Classifier: License :: OSI Approved :: MIT License
Classifier: Programming Language :: Python :: 3.10
Classifier: Programming Language :: Python :: 3.11
Classifier: Programming Language :: Python :: 3.12
Requires-Python: >=3.10
Requires-Dist: djangorestframework>=3.14.0
Requires-Dist: permission-manager>=0.6.0
